CHANGES.txt
MANIFEST.in
README.txt
setup.cfg
setup.py
js/__init__.py
js/__init__.pyc
js.html5_upload.egg-info/PKG-INFO
js.html5_upload.egg-info/SOURCES.txt
js.html5_upload.egg-info/dependency_links.txt
js.html5_upload.egg-info/entry_points.txt
js.html5_upload.egg-info/namespace_packages.txt
js.html5_upload.egg-info/not-zip-safe
js.html5_upload.egg-info/requires.txt
js.html5_upload.egg-info/top_level.txt
js/html5_upload/__init__.py
js/html5_upload/__init__.pyc
js/html5_upload/test_html5_upload.js.txt
js/html5_upload/resources/example.html
js/html5_upload/resources/html5_upload.js