Metadata-Version: 1.0
Name: js.html5-upload
Version: 0.1
Summary: Fanstatic packaging of jquery-html5-upload
Home-page: UNKNOWN
Author: UNKNOWN
Author-email: UNKNOWN
License: UNKNOWN
Platform: UNKNOWN
